{
  "version": "3.3.10",
  "flags": {},
  "shapes": [
    {
      "kie_linking": [],
      "label": "Healthy_Apple",
      "score": null,
      "points": [
        [
          217.0,
          20.0
        ],
        [
          216.0,
          29.0
        ],
        [
          222.0,
          42.0
        ],
        [
          222.0,
          49.0
        ],
        [
          212.0,
          48.0
        ],
        [
          189.0,
          53.0
        ],
        [
          147.0,
          68.0
        ],
        [
          119.0,
          87.0
        ],
        [
          93.0,
          116.0
        ],
        [
          77.0,
          146.0
        ],
        [
          69.0,
          169.0
        ],
        [
          62.0,
          215.0
        ],
        [
          63.0,
          251.0
        ],
        [
          70.0,
          292.0
        ],
        [
          85.0,
          336.0
        ],
        [
          118.0,
          393.0
        ],
        [
          142.0,
          426.0
        ],
        [
          167.0,
          444.0
        ],
        [
          203.0,
          459.0
        ],
        [
          261.0,
          460.0
        ],
        [
          261.0,
          465.0
        ],
        [
          263.0,
          467.0
        ],
        [
          268.0,
          464.0
        ],
        [
          274.0,
          474.0
        ],
        [
          275.0,
          460.0
        ],
        [
          283.0,
          453.0
        ],
        [
          289.0,
          453.0
        ],
        [
          293.0,
          456.0
        ],
        [
          296.0,
          456.0
        ],
        [
          299.0,
          452.0
        ],
        [
          317.0,
          455.0
        ],
        [
          335.0,
          454.0
        ],
        [
          358.0,
          448.0
        ],
        [
          373.0,
          439.0
        ],
        [
          391.0,
          424.0
        ],
        [
          408.0,
          403.0
        ],
        [
          432.0,
          359.0
        ],
        [
          443.0,
          323.0
        ],
        [
          450.0,
          283.0
        ],
        [
          450.0,
          217.0
        ],
        [
          442.0,
          182.0
        ],
        [
          426.0,
          141.0
        ],
        [
          409.0,
          113.0
        ],
        [
          375.0,
          78.0
        ],
        [
          335.0,
          55.0
        ],
        [
          312.0,
          48.0
        ],
        [
          280.0,
          45.0
        ],
        [
          252.0,
          45.0
        ],
        [
          240.0,
          48.0
        ],
        [
          235.0,
          42.0
        ],
        [
          232.0,
          29.0
        ],
        [
          226.0,
          20.0
        ]
      ],
      "group_id": null,
      "description": "",
      "difficult": false,
      "shape_type": "polygon",
      "flags": {},
      "attributes": {}
    },
    {
      "kie_linking": [],
      "label": "Scab",
      "score": null,
      "points": [
        [
          131.0,
          234.0
        ],
        [
          127.0,
          238.0
        ],
        [
          126.0,
          241.0
        ],
        [
          124.0,
          243.0
        ],
        [
          123.0,
          247.0
        ],
        [
          121.0,
          248.0
        ],
        [
          121.0,
          250.0
        ],
        [
          119.0,
          253.0
        ],
        [
          119.0,
          255.0
        ],
        [
          117.0,
          256.0
        ],
        [
          116.0,
          258.0
        ],
        [
          116.0,
          263.0
        ],
        [
          114.0,
          265.0
        ],
        [
          113.0,
          265.0
        ],
        [
          113.0,
          267.0
        ],
        [
          112.0,
          268.0
        ],
        [
          112.0,
          275.0
        ],
        [
          109.0,
          277.0
        ],
        [
          109.0,
          278.0
        ],
        [
          110.0,
          278.0
        ],
        [
          112.0,
          280.0
        ],
        [
          112.0,
          282.0
        ],
        [
          111.0,
          283.0
        ],
        [
          111.0,
          287.0
        ],
        [
          112.0,
          288.0
        ],
        [
          112.0,
          302.0
        ],
        [
          113.0,
          303.0
        ],
        [
          113.0,
          308.0
        ],
        [
          115.0,
          310.0
        ],
        [
          115.0,
          316.0
        ],
        [
          116.0,
          317.0
        ],
        [
          116.0,
          322.0
        ],
        [
          117.0,
          323.0
        ],
        [
          117.0,
          325.0
        ],
        [
          120.0,
          328.0
        ],
        [
          120.0,
          332.0
        ],
        [
          121.0,
          333.0
        ],
        [
          121.0,
          339.0
        ],
        [
          123.0,
          341.0
        ],
        [
          128.0,
          351.0
        ],
        [
          130.0,
          352.0
        ],
        [
          133.0,
          356.0
        ],
        [
          133.0,
          357.0
        ],
        [
          135.0,
          358.0
        ],
        [
          136.0,
          360.0
        ],
        [
          136.0,
          364.0
        ],
        [
          137.0,
          365.0
        ],
        [
          137.0,
          367.0
        ],
        [
          139.0,
          367.0
        ],
        [
          141.0,
          369.0
        ],
        [
          141.0,
          370.0
        ],
        [
          142.0,
          370.0
        ],
        [
          144.0,
          372.0
        ],
        [
          144.0,
          374.0
        ],
        [
          145.0,
          375.0
        ],
        [
          146.0,
          375.0
        ],
        [
          153.0,
          381.0
        ],
        [
          155.0,
          381.0
        ],
        [
          157.0,
          383.0
        ],
        [
          158.0,
          382.0
        ],
        [
          162.0,
          384.0
        ],
        [
          165.0,
          384.0
        ],
        [
          169.0,
          387.0
        ],
        [
          170.0,
          386.0
        ],
        [
          173.0,
          386.0
        ],
        [
          174.0,
          385.0
        ],
        [
          177.0,
          386.0
        ],
        [
          180.0,
          384.0
        ],
        [
          185.0,
          384.0
        ],
        [
          186.0,
          383.0
        ],
        [
          190.0,
          383.0
        ],
        [
          197.0,
          379.0
        ],
        [
          199.0,
          379.0
        ],
        [
          200.0,
          378.0
        ],
        [
          202.0,
          378.0
        ],
        [
          205.0,
          376.0
        ],
        [
          209.0,
          375.0
        ],
        [
          213.0,
          371.0
        ],
        [
          214.0,
          371.0
        ],
        [
          216.0,
          368.0
        ],
        [
          217.0,
          368.0
        ],
        [
          219.0,
          366.0
        ],
        [
          219.0,
          364.0
        ],
        [
          221.0,
          362.0
        ],
        [
          223.0,
          358.0
        ],
        [
          223.0,
          353.0
        ],
        [
          226.0,
          350.0
        ],
        [
          226.0,
          349.0
        ],
        [
          224.0,
          347.0
        ],
        [
          224.0,
          344.0
        ],
        [
          227.0,
          341.0
        ],
        [
          229.0,
          340.0
        ],
        [
          233.0,
          340.0
        ],
        [
          235.0,
          338.0
        ],
        [
          235.0,
          337.0
        ],
        [
          233.0,
          335.0
        ],
        [
          233.0,
          320.0
        ],
        [
          232.0,
          319.0
        ],
        [
          232.0,
          317.0
        ],
        [
          234.0,
          314.0
        ],
        [
          233.0,
          313.0
        ],
        [
          233.0,
          300.0
        ],
        [
          234.0,
          299.0
        ],
        [
          232.0,
          295.0
        ],
        [
          232.0,
          289.0
        ],
        [
          231.0,
          288.0
        ],
        [
          231.0,
          286.0
        ],
        [
          228.0,
          280.0
        ],
        [
          226.0,
          278.0
        ],
        [
          226.0,
          276.0
        ],
        [
          224.0,
          274.0
        ],
        [
          224.0,
          272.0
        ],
        [
          223.0,
          271.0
        ],
        [
          223.0,
          266.0
        ],
        [
          222.0,
          265.0
        ],
        [
          222.0,
          262.0
        ],
        [
          220.0,
          260.0
        ],
        [
          213.0,
          257.0
        ],
        [
          211.0,
          255.0
        ],
        [
          209.0,
          255.0
        ],
        [
          201.0,
          248.0
        ],
        [
          200.0,
          248.0
        ],
        [
          198.0,
          244.0
        ],
        [
          197.0,
          244.0
        ],
        [
          194.0,
          240.0
        ],
        [
          193.0,
          240.0
        ],
        [
          190.0,
          237.0
        ],
        [
          186.0,
          235.0
        ],
        [
          180.0,
          235.0
        ],
        [
          179.0,
          234.0
        ],
        [
          155.0,
          234.0
        ],
        [
          154.0,
          233.0
        ],
        [
          149.0,
          233.0
        ],
        [
          148.0,
          232.0
        ],
        [
          140.0,
          232.0
        ],
        [
          139.0,
          233.0
        ],
        [
          135.0,
          233.0
        ],
        [
          134.0,
          234.0
        ]
      ],
      "group_id": null,
      "description": "",
      "difficult": false,
      "shape_type": "polygon",
      "flags": {},
      "attributes": {}
    },
    {
      "kie_linking": [],
      "label": "Scab",
      "score": null,
      "points": [
        [
          258.0,
          139.0
        ],
        [
          252.0,
          143.0
        ],
        [
          248.0,
          148.0
        ],
        [
          245.0,
          157.0
        ],
        [
          244.0,
          170.0
        ],
        [
          240.0,
          181.0
        ],
        [
          240.0,
          187.0
        ],
        [
          238.0,
          192.0
        ],
        [
          238.0,
          203.0
        ],
        [
          236.0,
          210.0
        ],
        [
          236.0,
          247.0
        ],
        [
          242.0,
          261.0
        ],
        [
          251.0,
          271.0
        ],
        [
          255.0,
          273.0
        ],
        [
          256.0,
          276.0
        ],
        [
          259.0,
          279.0
        ],
        [
          262.0,
          280.0
        ],
        [
          267.0,
          285.0
        ],
        [
          270.0,
          290.0
        ],
        [
          271.0,
          297.0
        ],
        [
          266.0,
          301.0
        ],
        [
          261.0,
          309.0
        ],
        [
          261.0,
          313.0
        ],
        [
          259.0,
          316.0
        ],
        [
          259.0,
          322.0
        ],
        [
          257.0,
          325.0
        ],
        [
          256.0,
          332.0
        ],
        [
          254.0,
          334.0
        ],
        [
          254.0,
          336.0
        ],
        [
          245.0,
          341.0
        ],
        [
          235.0,
          341.0
        ],
        [
          233.0,
          344.0
        ],
        [
          231.0,
          343.0
        ],
        [
          231.0,
          341.0
        ],
        [
          228.0,
          341.0
        ],
        [
          228.0,
          342.0
        ],
        [
          234.0,
          347.0
        ],
        [
          236.0,
          346.0
        ],
        [
          244.0,
          346.0
        ],
        [
          245.0,
          345.0
        ],
        [
          246.0,
          346.0
        ],
        [
          249.0,
          343.0
        ],
        [
          250.0,
          344.0
        ],
        [
          251.0,
          343.0
        ],
        [
          261.0,
          343.0
        ],
        [
          264.0,
          347.0
        ],
        [
          267.0,
          357.0
        ],
        [
          267.0,
          361.0
        ],
        [
          279.0,
          380.0
        ],
        [
          285.0,
          381.0
        ],
        [
          291.0,
          379.0
        ],
        [
          296.0,
          379.0
        ],
        [
          305.0,
          382.0
        ],
        [
          315.0,
          382.0
        ],
        [
          317.0,
          380.0
        ],
        [
          323.0,
          379.0
        ],
        [
          331.0,
          370.0
        ],
        [
          332.0,
          366.0
        ],
        [
          335.0,
          363.0
        ],
        [
          338.0,
          362.0
        ],
        [
          342.0,
          356.0
        ],
        [
          346.0,
          355.0
        ],
        [
          351.0,
          349.0
        ],
        [
          365.0,
          341.0
        ],
        [
          369.0,
          340.0
        ],
        [
          373.0,
          336.0
        ],
        [
          379.0,
          334.0
        ],
        [
          390.0,
          318.0
        ],
        [
          394.0,
          306.0
        ],
        [
          395.0,
          295.0
        ],
        [
          396.0,
          294.0
        ],
        [
          396.0,
          263.0
        ],
        [
          395.0,
          262.0
        ],
        [
          395.0,
          257.0
        ],
        [
          391.0,
          247.0
        ],
        [
          387.0,
          243.0
        ],
        [
          375.0,
          239.0
        ],
        [
          369.0,
          233.0
        ],
        [
          363.0,
          229.0
        ],
        [
          361.0,
          229.0
        ],
        [
          356.0,
          225.0
        ],
        [
          351.0,
          212.0
        ],
        [
          346.0,
          185.0
        ],
        [
          344.0,
          183.0
        ],
        [
          339.0,
          169.0
        ],
        [
          330.0,
          157.0
        ],
        [
          314.0,
          141.0
        ],
        [
          306.0,
          136.0
        ],
        [
          276.0,
          137.0
        ],
        [
          271.0,
          139.0
        ]
      ],
      "group_id": null,
      "description": "",
      "difficult": false,
      "shape_type": "polygon",
      "flags": {},
      "attributes": {}
    },
    {
      "kie_linking": [],
      "label": "Scab",
      "score": null,
      "points": [
        [
          325.0,
          404.0
        ],
        [
          321.0,
          404.0
        ],
        [
          318.0,
          407.0
        ],
        [
          318.0,
          408.0
        ],
        [
          317.0,
          409.0
        ],
        [
          317.0,
          410.0
        ],
        [
          316.0,
          411.0
        ],
        [
          316.0,
          412.0
        ],
        [
          315.0,
          413.0
        ],
        [
          315.0,
          417.0
        ],
        [
          316.0,
          418.0
        ],
        [
          317.0,
          418.0
        ],
        [
          320.0,
          421.0
        ],
        [
          320.0,
          422.0
        ],
        [
          321.0,
          423.0
        ],
        [
          321.0,
          425.0
        ],
        [
          322.0,
          426.0
        ],
        [
          321.0,
          425.0
        ],
        [
          322.0,
          424.0
        ],
        [
          325.0,
          424.0
        ],
        [
          327.0,
          422.0
        ],
        [
          327.0,
          421.0
        ],
        [
          328.0,
          420.0
        ],
        [
          328.0,
          418.0
        ],
        [
          329.0,
          417.0
        ],
        [
          329.0,
          415.0
        ],
        [
          330.0,
          414.0
        ],
        [
          330.0,
          409.0
        ],
        [
          329.0,
          408.0
        ],
        [
          329.0,
          407.0
        ],
        [
          327.0,
          405.0
        ],
        [
          326.0,
          405.0
        ]
      ],
      "group_id": null,
      "description": "",
      "difficult": false,
      "shape_type": "polygon",
      "flags": {},
      "attributes": {}
    },
    {
      "kie_linking": [],
      "label": "Scab",
      "score": null,
      "points": [
        [
          259.0,
          389.0
        ],
        [
          255.0,
          389.0
        ],
        [
          254.0,
          390.0
        ],
        [
          252.0,
          390.0
        ],
        [
          251.0,
          391.0
        ],
        [
          249.0,
          391.0
        ],
        [
          247.0,
          393.0
        ],
        [
          247.0,
          394.0
        ],
        [
          246.0,
          395.0
        ],
        [
          246.0,
          399.0
        ],
        [
          244.0,
          401.0
        ],
        [
          245.0,
          402.0
        ],
        [
          245.0,
          404.0
        ],
        [
          246.0,
          404.0
        ],
        [
          249.0,
          407.0
        ],
        [
          248.0,
          408.0
        ],
        [
          249.0,
          408.0
        ],
        [
          250.0,
          409.0
        ],
        [
          253.0,
          409.0
        ],
        [
          254.0,
          410.0
        ],
        [
          255.0,
          410.0
        ],
        [
          256.0,
          409.0
        ],
        [
          260.0,
          409.0
        ],
        [
          261.0,
          408.0
        ],
        [
          264.0,
          408.0
        ],
        [
          263.0,
          408.0
        ],
        [
          262.0,
          407.0
        ],
        [
          263.0,
          406.0
        ],
        [
          264.0,
          406.0
        ],
        [
          265.0,
          405.0
        ],
        [
          265.0,
          404.0
        ],
        [
          266.0,
          403.0
        ],
        [
          266.0,
          400.0
        ],
        [
          267.0,
          399.0
        ],
        [
          268.0,
          400.0
        ],
        [
          267.0,
          399.0
        ],
        [
          267.0,
          396.0
        ],
        [
          268.0,
          395.0
        ],
        [
          268.0,
          394.0
        ],
        [
          266.0,
          394.0
        ],
        [
          265.0,
          393.0
        ],
        [
          265.0,
          392.0
        ],
        [
          264.0,
          391.0
        ],
        [
          263.0,
          391.0
        ],
        [
          262.0,
          390.0
        ],
        [
          260.0,
          390.0
        ]
      ],
      "group_id": null,
      "description": "",
      "difficult": false,
      "shape_type": "polygon",
      "flags": {},
      "attributes": {}
    },
    {
      "kie_linking": [],
      "label": "Scab",
      "score": null,
      "points": [
        [
          214.0,
          406.0
        ],
        [
          213.0,
          405.0
        ],
        [
          213.0,
          404.0
        ],
        [
          209.0,
          400.0
        ],
        [
          209.0,
          399.0
        ],
        [
          207.0,
          399.0
        ],
        [
          206.0,
          398.0
        ],
        [
          201.0,
          398.0
        ],
        [
          200.0,
          399.0
        ],
        [
          199.0,
          399.0
        ],
        [
          198.0,
          400.0
        ],
        [
          196.0,
          400.0
        ],
        [
          196.0,
          401.0
        ],
        [
          195.0,
          402.0
        ],
        [
          180.0,
          402.0
        ],
        [
          179.0,
          403.0
        ],
        [
          178.0,
          403.0
        ],
        [
          178.0,
          404.0
        ],
        [
          176.0,
          406.0
        ],
        [
          176.0,
          409.0
        ],
        [
          177.0,
          410.0
        ],
        [
          177.0,
          411.0
        ],
        [
          180.0,
          414.0
        ],
        [
          185.0,
          414.0
        ],
        [
          186.0,
          415.0
        ],
        [
          188.0,
          415.0
        ],
        [
          189.0,
          416.0
        ],
        [
          190.0,
          415.0
        ],
        [
          191.0,
          415.0
        ],
        [
          192.0,
          416.0
        ],
        [
          193.0,
          416.0
        ],
        [
          194.0,
          415.0
        ],
        [
          195.0,
          415.0
        ],
        [
          196.0,
          414.0
        ],
        [
          199.0,
          414.0
        ],
        [
          201.0,
          416.0
        ],
        [
          204.0,
          416.0
        ],
        [
          206.0,
          414.0
        ],
        [
          207.0,
          414.0
        ],
        [
          208.0,
          413.0
        ],
        [
          209.0,
          413.0
        ],
        [
          212.0,
          410.0
        ],
        [
          213.0,
          410.0
        ],
        [
          214.0,
          409.0
        ]
      ],
      "group_id": null,
      "description": "",
      "difficult": false,
      "shape_type": "polygon",
      "flags": {},
      "attributes": {}
    },
    {
      "kie_linking": [],
      "label": "Scab",
      "score": null,
      "points": [
        [
          162.0,
          432.0
        ],
        [
          161.0,
          433.0
        ],
        [
          161.0,
          436.0
        ],
        [
          162.0,
          437.0
        ],
        [
          162.0,
          439.0
        ],
        [
          167.0,
          444.0
        ],
        [
          168.0,
          444.0
        ],
        [
          169.0,
          445.0
        ],
        [
          173.0,
          445.0
        ],
        [
          173.0,
          441.0
        ],
        [
          172.0,
          440.0
        ],
        [
          172.0,
          439.0
        ],
        [
          169.0,
          436.0
        ],
        [
          169.0,
          435.0
        ],
        [
          167.0,
          433.0
        ],
        [
          166.0,
          433.0
        ],
        [
          165.0,
          432.0
        ]
      ],
      "group_id": null,
      "description": "",
      "difficult": false,
      "shape_type": "polygon",
      "flags": {},
      "attributes": {}
    },
    {
      "kie_linking": [],
      "label": "Scab",
      "score": null,
      "points": [
        [
          186.0,
          446.0
        ],
        [
          186.0,
          451.0
        ],
        [
          189.0,
          454.0
        ],
        [
          190.0,
          454.0
        ],
        [
          191.0,
          455.0
        ],
        [
          196.0,
          455.0
        ],
        [
          196.0,
          452.0
        ],
        [
          195.0,
          451.0
        ],
        [
          195.0,
          450.0
        ],
        [
          191.0,
          446.0
        ]
      ],
      "group_id": null,
      "description": "",
      "difficult": false,
      "shape_type": "polygon",
      "flags": {},
      "attributes": {}
    },
    {
      "kie_linking": [],
      "label": "Scab",
      "score": null,
      "points": [
        [
          246.0,
          433.0
        ],
        [
          239.0,
          433.0
        ],
        [
          238.0,
          434.0
        ],
        [
          234.0,
          434.0
        ],
        [
          234.0,
          435.0
        ],
        [
          233.0,
          436.0
        ],
        [
          232.0,
          436.0
        ],
        [
          231.0,
          435.0
        ],
        [
          229.0,
          437.0
        ],
        [
          230.0,
          438.0
        ],
        [
          230.0,
          440.0
        ],
        [
          231.0,
          441.0
        ],
        [
          231.0,
          442.0
        ],
        [
          232.0,
          443.0
        ],
        [
          232.0,
          445.0
        ],
        [
          234.0,
          447.0
        ],
        [
          233.0,
          448.0
        ],
        [
          234.0,
          447.0
        ],
        [
          235.0,
          448.0
        ],
        [
          237.0,
          448.0
        ],
        [
          238.0,
          449.0
        ],
        [
          239.0,
          448.0
        ],
        [
          240.0,
          448.0
        ],
        [
          241.0,
          447.0
        ],
        [
          242.0,
          447.0
        ],
        [
          243.0,
          446.0
        ],
        [
          244.0,
          446.0
        ],
        [
          245.0,
          445.0
        ],
        [
          247.0,
          445.0
        ],
        [
          250.0,
          442.0
        ],
        [
          250.0,
          441.0
        ],
        [
          249.0,
          440.0
        ],
        [
          249.0,
          439.0
        ],
        [
          248.0,
          438.0
        ],
        [
          248.0,
          436.0
        ],
        [
          247.0,
          435.0
        ],
        [
          247.0,
          434.0
        ]
      ],
      "group_id": null,
      "description": "",
      "difficult": false,
      "shape_type": "polygon",
      "flags": {},
      "attributes": {}
    },
    {
      "kie_linking": [],
      "label": "Scab",
      "score": null,
      "points": [
        [
          259.0,
          437.0
        ],
        [
          257.0,
          435.0
        ],
        [
          254.0,
          435.0
        ],
        [
          253.0,
          436.0
        ],
        [
          252.0,
          436.0
        ],
        [
          251.0,
          437.0
        ],
        [
          250.0,
          437.0
        ],
        [
          249.0,
          438.0
        ],
        [
          246.0,
          438.0
        ],
        [
          246.0,
          441.0
        ],
        [
          247.0,
          442.0
        ],
        [
          247.0,
          443.0
        ],
        [
          248.0,
          444.0
        ],
        [
          251.0,
          444.0
        ],
        [
          252.0,
          445.0
        ],
        [
          257.0,
          445.0
        ],
        [
          258.0,
          444.0
        ],
        [
          258.0,
          443.0
        ],
        [
          259.0,
          442.0
        ],
        [
          259.0,
          441.0
        ],
        [
          260.0,
          440.0
        ],
        [
          260.0,
          439.0
        ],
        [
          259.0,
          438.0
        ]
      ],
      "group_id": null,
      "description": "",
      "difficult": false,
      "shape_type": "polygon",
      "flags": {},
      "attributes": {}
    },
    {
      "kie_linking": [],
      "label": "Scab",
      "score": null,
      "points": [
        [
          230.0,
          451.0
        ],
        [
          230.0,
          452.0
        ],
        [
          229.0,
          453.0
        ],
        [
          229.0,
          454.0
        ],
        [
          228.0,
          455.0
        ],
        [
          228.0,
          457.0
        ],
        [
          229.0,
          458.0
        ],
        [
          229.0,
          460.0
        ],
        [
          243.0,
          460.0
        ],
        [
          243.0,
          459.0
        ],
        [
          244.0,
          458.0
        ],
        [
          244.0,
          456.0
        ],
        [
          243.0,
          455.0
        ],
        [
          243.0,
          454.0
        ],
        [
          240.0,
          451.0
        ],
        [
          239.0,
          451.0
        ],
        [
          238.0,
          450.0
        ],
        [
          234.0,
          450.0
        ],
        [
          233.0,
          451.0
        ]
      ],
      "group_id": null,
      "description": "",
      "difficult": false,
      "shape_type": "polygon",
      "flags": {},
      "attributes": {}
    },
    {
      "kie_linking": [],
      "label": "Scab",
      "score": null,
      "points": [
        [
          325.0,
          426.0
        ],
        [
          321.0,
          426.0
        ],
        [
          320.0,
          427.0
        ],
        [
          319.0,
          427.0
        ],
        [
          318.0,
          428.0
        ],
        [
          318.0,
          429.0
        ],
        [
          317.0,
          430.0
        ],
        [
          316.0,
          430.0
        ],
        [
          315.0,
          431.0
        ],
        [
          315.0,
          433.0
        ],
        [
          314.0,
          434.0
        ],
        [
          314.0,
          435.0
        ],
        [
          312.0,
          437.0
        ],
        [
          312.0,
          438.0
        ],
        [
          311.0,
          439.0
        ],
        [
          311.0,
          442.0
        ],
        [
          312.0,
          443.0
        ],
        [
          312.0,
          444.0
        ],
        [
          319.0,
          444.0
        ],
        [
          320.0,
          443.0
        ],
        [
          321.0,
          443.0
        ],
        [
          322.0,
          442.0
        ],
        [
          323.0,
          442.0
        ],
        [
          324.0,
          441.0
        ],
        [
          326.0,
          441.0
        ],
        [
          326.0,
          439.0
        ],
        [
          327.0,
          438.0
        ],
        [
          327.0,
          435.0
        ],
        [
          326.0,
          434.0
        ],
        [
          326.0,
          430.0
        ],
        [
          325.0,
          429.0
        ]
      ],
      "group_id": null,
      "description": "",
      "difficult": false,
      "shape_type": "polygon",
      "flags": {},
      "attributes": {}
    },
    {
      "kie_linking": [],
      "label": "Scab",
      "score": null,
      "points": [
        [
          333.0,
          384.0
        ],
        [
          331.0,
          386.0
        ],
        [
          331.0,
          392.0
        ],
        [
          332.0,
          393.0
        ],
        [
          333.0,
          393.0
        ],
        [
          334.0,
          394.0
        ],
        [
          340.0,
          394.0
        ],
        [
          342.0,
          392.0
        ],
        [
          342.0,
          390.0
        ],
        [
          343.0,
          389.0
        ],
        [
          343.0,
          388.0
        ],
        [
          342.0,
          387.0
        ],
        [
          342.0,
          386.0
        ],
        [
          339.0,
          383.0
        ],
        [
          335.0,
          383.0
        ],
        [
          334.0,
          384.0
        ]
      ],
      "group_id": null,
      "description": "",
      "difficult": false,
      "shape_type": "polygon",
      "flags": {},
      "attributes": {}
    },
    {
      "kie_linking": [],
      "label": "Scab",
      "score": null,
      "points": [
        [
          223.0,
          270.0
        ],
        [
          223.0,
          273.0
        ],
        [
          222.0,
          274.0
        ],
        [
          222.0,
          275.0
        ],
        [
          223.0,
          275.0
        ],
        [
          224.0,
          276.0
        ],
        [
          224.0,
          277.0
        ],
        [
          223.0,
          278.0
        ],
        [
          222.0,
          278.0
        ],
        [
          222.0,
          279.0
        ],
        [
          224.0,
          281.0
        ],
        [
          225.0,
          281.0
        ],
        [
          231.0,
          287.0
        ],
        [
          231.0,
          286.0
        ],
        [
          232.0,
          285.0
        ],
        [
          233.0,
          285.0
        ],
        [
          234.0,
          286.0
        ],
        [
          234.0,
          287.0
        ],
        [
          235.0,
          287.0
        ],
        [
          236.0,
          286.0
        ],
        [
          236.0,
          285.0
        ],
        [
          237.0,
          284.0
        ],
        [
          237.0,
          283.0
        ],
        [
          238.0,
          282.0
        ],
        [
          238.0,
          280.0
        ],
        [
          239.0,
          279.0
        ],
        [
          239.0,
          271.0
        ],
        [
          238.0,
          270.0
        ],
        [
          232.0,
          270.0
        ],
        [
          231.0,
          269.0
        ],
        [
          226.0,
          269.0
        ],
        [
          224.0,
          271.0
        ]
      ],
      "group_id": null,
      "description": "",
      "difficult": false,
      "shape_type": "polygon",
      "flags": {},
      "attributes": {}
    },
    {
      "kie_linking": [],
      "label": "Scab",
      "score": null,
      "points": [
        [
          242.0,
          47.0
        ],
        [
          242.0,
          55.0
        ],
        [
          243.0,
          56.0
        ],
        [
          243.0,
          59.0
        ],
        [
          244.0,
          60.0
        ],
        [
          244.0,
          63.0
        ],
        [
          246.0,
          65.0
        ],
        [
          246.0,
          67.0
        ],
        [
          247.0,
          67.0
        ],
        [
          247.0,
          66.0
        ],
        [
          248.0,
          65.0
        ],
        [
          253.0,
          65.0
        ],
        [
          257.0,
          69.0
        ],
        [
          258.0,
          68.0
        ],
        [
          261.0,
          68.0
        ],
        [
          262.0,
          67.0
        ],
        [
          263.0,
          67.0
        ],
        [
          264.0,
          68.0
        ],
        [
          268.0,
          68.0
        ],
        [
          269.0,
          67.0
        ],
        [
          271.0,
          67.0
        ],
        [
          272.0,
          68.0
        ],
        [
          273.0,
          68.0
        ],
        [
          274.0,
          67.0
        ],
        [
          275.0,
          67.0
        ],
        [
          276.0,
          66.0
        ],
        [
          277.0,
          66.0
        ],
        [
          278.0,
          65.0
        ],
        [
          279.0,
          65.0
        ],
        [
          280.0,
          64.0
        ],
        [
          280.0,
          63.0
        ],
        [
          287.0,
          56.0
        ],
        [
          287.0,
          54.0
        ],
        [
          286.0,
          53.0
        ],
        [
          286.0,
          52.0
        ],
        [
          287.0,
          51.0
        ],
        [
          287.0,
          50.0
        ],
        [
          286.0,
          49.0
        ],
        [
          286.0,
          48.0
        ],
        [
          287.0,
          47.0
        ],
        [
          288.0,
          47.0
        ],
        [
          287.0,
          46.0
        ],
        [
          280.0,
          46.0
        ],
        [
          279.0,
          45.0
        ],
        [
          249.0,
          45.0
        ],
        [
          248.0,
          46.0
        ],
        [
          243.0,
          46.0
        ]
      ],
      "group_id": null,
      "description": "",
      "difficult": false,
      "shape_type": "polygon",
      "flags": {},
      "attributes": {}
    },
    {
      "kie_linking": [],
      "label": "Scab",
      "score": null,
      "points": [
        [
          314.0,
          82.0
        ],
        [
          313.0,
          82.0
        ],
        [
          311.0,
          80.0
        ],
        [
          311.0,
          79.0
        ],
        [
          300.0,
          79.0
        ],
        [
          298.0,
          81.0
        ],
        [
          297.0,
          81.0
        ],
        [
          296.0,
          82.0
        ],
        [
          295.0,
          82.0
        ],
        [
          294.0,
          83.0
        ],
        [
          293.0,
          83.0
        ],
        [
          292.0,
          84.0
        ],
        [
          291.0,
          84.0
        ],
        [
          289.0,
          86.0
        ],
        [
          289.0,
          87.0
        ],
        [
          288.0,
          88.0
        ],
        [
          288.0,
          89.0
        ],
        [
          289.0,
          90.0
        ],
        [
          289.0,
          92.0
        ],
        [
          291.0,
          92.0
        ],
        [
          292.0,
          91.0
        ],
        [
          293.0,
          92.0
        ],
        [
          293.0,
          93.0
        ],
        [
          294.0,
          94.0
        ],
        [
          295.0,
          94.0
        ],
        [
          296.0,
          93.0
        ],
        [
          297.0,
          93.0
        ],
        [
          298.0,
          94.0
        ],
        [
          301.0,
          94.0
        ],
        [
          302.0,
          93.0
        ],
        [
          306.0,
          93.0
        ],
        [
          307.0,
          92.0
        ],
        [
          308.0,
          92.0
        ],
        [
          309.0,
          91.0
        ],
        [
          310.0,
          91.0
        ],
        [
          312.0,
          89.0
        ],
        [
          313.0,
          89.0
        ],
        [
          313.0,
          85.0
        ],
        [
          314.0,
          84.0
        ]
      ],
      "group_id": null,
      "description": "",
      "difficult": false,
      "shape_type": "polygon",
      "flags": {},
      "attributes": {}
    },
    {
      "kie_linking": [],
      "label": "Scab",
      "score": null,
      "points": [
        [
          402.0,
          347.0
        ],
        [
          403.0,
          348.0
        ],
        [
          403.0,
          350.0
        ],
        [
          404.0,
          350.0
        ],
        [
          405.0,
          351.0
        ],
        [
          406.0,
          351.0
        ],
        [
          407.0,
          352.0
        ],
        [
          411.0,
          352.0
        ],
        [
          412.0,
          353.0
        ],
        [
          420.0,
          353.0
        ],
        [
          421.0,
          352.0
        ],
        [
          422.0,
          352.0
        ],
        [
          422.0,
          351.0
        ],
        [
          427.0,
          346.0
        ],
        [
          427.0,
          345.0
        ],
        [
          426.0,
          344.0
        ],
        [
          426.0,
          342.0
        ],
        [
          425.0,
          341.0
        ],
        [
          425.0,
          339.0
        ],
        [
          424.0,
          339.0
        ],
        [
          423.0,
          338.0
        ],
        [
          413.0,
          338.0
        ],
        [
          412.0,
          339.0
        ],
        [
          410.0,
          339.0
        ],
        [
          410.0,
          340.0
        ],
        [
          409.0,
          341.0
        ],
        [
          406.0,
          341.0
        ],
        [
          404.0,
          343.0
        ],
        [
          404.0,
          345.0
        ]
      ],
      "group_id": null,
      "description": "",
      "difficult": false,
      "shape_type": "polygon",
      "flags": {},
      "attributes": {}
    },
    {
      "kie_linking": [],
      "label": "Scab",
      "score": null,
      "points": [
        [
          133.0,
          217.0
        ],
        [
          127.0,
          217.0
        ],
        [
          126.0,
          218.0
        ],
        [
          123.0,
          218.0
        ],
        [
          119.0,
          222.0
        ],
        [
          119.0,
          229.0
        ],
        [
          121.0,
          231.0
        ],
        [
          121.0,
          232.0
        ],
        [
          122.0,
          232.0
        ],
        [
          123.0,
          233.0
        ],
        [
          129.0,
          233.0
        ],
        [
          130.0,
          232.0
        ],
        [
          131.0,
          232.0
        ],
        [
          132.0,
          231.0
        ],
        [
          133.0,
          231.0
        ],
        [
          135.0,
          229.0
        ],
        [
          136.0,
          229.0
        ],
        [
          136.0,
          221.0
        ],
        [
          135.0,
          220.0
        ],
        [
          135.0,
          219.0
        ]
      ],
      "group_id": null,
      "description": "",
      "difficult": false,
      "shape_type": "polygon",
      "flags": {},
      "attributes": {}
    },
    {
      "kie_linking": [],
      "label": "Scab",
      "score": null,
      "points": [
        [
          288.0,
          417.0
        ],
        [
          287.0,
          417.0
        ],
        [
          285.0,
          415.0
        ],
        [
          282.0,
          415.0
        ],
        [
          281.0,
          414.0
        ],
        [
          275.0,
          414.0
        ],
        [
          271.0,
          418.0
        ],
        [
          270.0,
          418.0
        ],
        [
          270.0,
          419.0
        ],
        [
          267.0,
          422.0
        ],
        [
          266.0,
          422.0
        ],
        [
          265.0,
          421.0
        ],
        [
          265.0,
          422.0
        ],
        [
          264.0,
          423.0
        ],
        [
          263.0,
          423.0
        ],
        [
          264.0,
          424.0
        ],
        [
          264.0,
          425.0
        ],
        [
          263.0,
          426.0
        ],
        [
          263.0,
          427.0
        ],
        [
          263.0,
          426.0
        ],
        [
          264.0,
          425.0
        ],
        [
          266.0,
          427.0
        ],
        [
          265.0,
          428.0
        ],
        [
          269.0,
          432.0
        ],
        [
          273.0,
          432.0
        ],
        [
          273.0,
          431.0
        ],
        [
          274.0,
          430.0
        ],
        [
          275.0,
          430.0
        ],
        [
          277.0,
          432.0
        ],
        [
          278.0,
          431.0
        ],
        [
          279.0,
          431.0
        ],
        [
          280.0,
          430.0
        ],
        [
          281.0,
          430.0
        ],
        [
          283.0,
          428.0
        ],
        [
          284.0,
          428.0
        ],
        [
          285.0,
          427.0
        ],
        [
          288.0,
          427.0
        ],
        [
          289.0,
          426.0
        ],
        [
          289.0,
          423.0
        ],
        [
          288.0,
          422.0
        ],
        [
          288.0,
          420.0
        ],
        [
          289.0,
          419.0
        ],
        [
          288.0,
          418.0
        ]
      ],
      "group_id": null,
      "description": "",
      "difficult": false,
      "shape_type": "polygon",
      "flags": {},
      "attributes": {}
    },
    {
      "kie_linking": [],
      "label": "Scab",
      "score": null,
      "points": [
        [
          286.0,
          402.0
        ],
        [
          286.0,
          409.0
        ],
        [
          287.0,
          410.0
        ],
        [
          287.0,
          412.0
        ],
        [
          288.0,
          413.0
        ],
        [
          289.0,
          413.0
        ],
        [
          291.0,
          415.0
        ],
        [
          291.0,
          416.0
        ],
        [
          292.0,
          417.0
        ],
        [
          293.0,
          417.0
        ],
        [
          294.0,
          416.0
        ],
        [
          293.0,
          416.0
        ],
        [
          292.0,
          415.0
        ],
        [
          294.0,
          413.0
        ],
        [
          296.0,
          413.0
        ],
        [
          297.0,
          412.0
        ],
        [
          298.0,
          412.0
        ],
        [
          299.0,
          411.0
        ],
        [
          300.0,
          411.0
        ],
        [
          301.0,
          410.0
        ],
        [
          306.0,
          410.0
        ],
        [
          306.0,
          407.0
        ],
        [
          305.0,
          406.0
        ],
        [
          305.0,
          402.0
        ],
        [
          304.0,
          401.0
        ],
        [
          303.0,
          402.0
        ],
        [
          301.0,
          400.0
        ],
        [
          299.0,
          400.0
        ],
        [
          298.0,
          399.0
        ],
        [
          295.0,
          399.0
        ],
        [
          294.0,
          398.0
        ],
        [
          291.0,
          398.0
        ],
        [
          290.0,
          399.0
        ],
        [
          289.0,
          399.0
        ]
      ],
      "group_id": null,
      "description": "",
      "difficult": false,
      "shape_type": "polygon",
      "flags": {},
      "attributes": {}
    },
    {
      "kie_linking": [],
      "label": "Scab",
      "score": null,
      "points": [
        [
          383.0,
          426.0
        ],
        [
          380.0,
          423.0
        ],
        [
          377.0,
          423.0
        ],
        [
          377.0,
          424.0
        ],
        [
          375.0,
          426.0
        ],
        [
          373.0,
          426.0
        ],
        [
          372.0,
          427.0
        ],
        [
          371.0,
          427.0
        ],
        [
          370.0,
          428.0
        ],
        [
          370.0,
          429.0
        ],
        [
          369.0,
          430.0
        ],
        [
          369.0,
          432.0
        ],
        [
          371.0,
          434.0
        ],
        [
          373.0,
          434.0
        ],
        [
          374.0,
          435.0
        ],
        [
          375.0,
          434.0
        ],
        [
          376.0,
          434.0
        ],
        [
          377.0,
          433.0
        ],
        [
          380.0,
          433.0
        ],
        [
          381.0,
          432.0
        ],
        [
          381.0,
          431.0
        ],
        [
          383.0,
          429.0
        ]
      ],
      "group_id": null,
      "description": "",
      "difficult": false,
      "shape_type": "polygon",
      "flags": {},
      "attributes": {}
    },
    {
      "kie_linking": [],
      "label": "Scab",
      "score": null,
      "points": [
        [
          352.0,
          443.0
        ],
        [
          350.0,
          441.0
        ],
        [
          349.0,
          441.0
        ],
        [
          348.0,
          440.0
        ],
        [
          344.0,
          440.0
        ],
        [
          343.0,
          441.0
        ],
        [
          341.0,
          441.0
        ],
        [
          340.0,
          442.0
        ],
        [
          339.0,
          442.0
        ],
        [
          338.0,
          443.0
        ],
        [
          337.0,
          443.0
        ],
        [
          335.0,
          445.0
        ],
        [
          335.0,
          448.0
        ],
        [
          338.0,
          451.0
        ],
        [
          338.0,
          452.0
        ],
        [
          348.0,
          452.0
        ],
        [
          350.0,
          450.0
        ],
        [
          351.0,
          450.0
        ],
        [
          352.0,
          449.0
        ],
        [
          352.0,
          448.0
        ],
        [
          353.0,
          447.0
        ],
        [
          353.0,
          446.0
        ],
        [
          352.0,
          445.0
        ]
      ],
      "group_id": null,
      "description": "",
      "difficult": false,
      "shape_type": "polygon",
      "flags": {},
      "attributes": {}
    },
    {
      "kie_linking": [],
      "label": "Scab",
      "score": null,
      "points": [
        [
          375.0,
          374.0
        ],
        [
          375.0,
          377.0
        ],
        [
          374.0,
          378.0
        ],
        [
          374.0,
          379.0
        ],
        [
          373.0,
          380.0
        ],
        [
          373.0,
          384.0
        ],
        [
          375.0,
          386.0
        ],
        [
          375.0,
          387.0
        ],
        [
          377.0,
          389.0
        ],
        [
          381.0,
          389.0
        ],
        [
          385.0,
          385.0
        ],
        [
          385.0,
          378.0
        ],
        [
          382.0,
          375.0
        ],
        [
          381.0,
          375.0
        ],
        [
          380.0,
          374.0
        ]
      ],
      "group_id": null,
      "description": "",
      "difficult": false,
      "shape_type": "polygon",
      "flags": {},
      "attributes": {}
    },
    {
      "kie_linking": [],
      "label": "Scab",
      "score": null,
      "points": [
        [
          221.0,
          431.0
        ],
        [
          218.0,
          434.0
        ],
        [
          218.0,
          436.0
        ],
        [
          219.0,
          437.0
        ],
        [
          219.0,
          439.0
        ],
        [
          220.0,
          439.0
        ],
        [
          222.0,
          441.0
        ],
        [
          222.0,
          442.0
        ],
        [
          223.0,
          443.0
        ],
        [
          223.0,
          444.0
        ],
        [
          228.0,
          449.0
        ],
        [
          232.0,
          449.0
        ],
        [
          233.0,
          448.0
        ],
        [
          233.0,
          446.0
        ],
        [
          237.0,
          442.0
        ],
        [
          238.0,
          442.0
        ],
        [
          237.0,
          441.0
        ],
        [
          237.0,
          440.0
        ],
        [
          236.0,
          439.0
        ],
        [
          235.0,
          439.0
        ],
        [
          233.0,
          437.0
        ],
        [
          233.0,
          436.0
        ],
        [
          232.0,
          435.0
        ],
        [
          232.0,
          434.0
        ],
        [
          231.0,
          433.0
        ],
        [
          231.0,
          432.0
        ],
        [
          229.0,
          430.0
        ],
        [
          223.0,
          430.0
        ],
        [
          222.0,
          431.0
        ]
      ],
      "group_id": null,
      "description": "",
      "difficult": false,
      "shape_type": "polygon",
      "flags": {},
      "attributes": {}
    }
  ],
  "imagePath": "scab_0006.jpg",
  "imageData": null,
  "imageHeight": 512,
  "imageWidth": 512,
  "description": ""
}