{
  "version": "3.3.10",
  "flags": {},
  "shapes": [
    {
      "label": "Healthy_Apple",
      "score": null,
      "points": [
        [
          295.0,
          22.0
        ],
        [
          251.0,
          20.0
        ],
        [
          211.0,
          27.0
        ],
        [
          168.0,
          46.0
        ],
        [
          133.0,
          71.0
        ],
        [
          85.0,
          117.0
        ],
        [
          61.0,
          148.0
        ],
        [
          37.0,
          194.0
        ],
        [
          24.0,
          245.0
        ],
        [
          23.0,
          278.0
        ],
        [
          31.0,
          325.0
        ],
        [
          60.0,
          392.0
        ],
        [
          90.0,
          427.0
        ],
        [
          122.0,
          454.0
        ],
        [
          168.0,
          479.0
        ],
        [
          218.0,
          493.0
        ],
        [
          278.0,
          492.0
        ],
        [
          315.0,
          483.0
        ],
        [
          346.0,
          472.0
        ],
        [
          402.0,
          441.0
        ],
        [
          447.0,
          399.0
        ],
        [
          466.0,
          376.0
        ],
        [
          486.0,
          334.0
        ],
        [
          499.0,
          287.0
        ],
        [
          501.0,
          242.0
        ],
        [
          496.0,
          209.0
        ],
        [
          488.0,
          181.0
        ],
        [
          478.0,
          158.0
        ],
        [
          456.0,
          122.0
        ],
        [
          421.0,
          83.0
        ],
        [
          391.0,
          59.0
        ],
        [
          346.0,
          36.0
        ]
      ],
      "group_id": null,
      "description": "",
      "difficult": false,
      "shape_type": "polygon",
      "flags": {},
      "attributes": {},
      "kie_linking": []
    },
    {
      "label": "Healthy_Apple",
      "score": null,
      "points": [
        [
          3.0,
          9.0
        ],
        [
          0.0,
          9.0
        ],
        [
          0.0,
          351.0
        ],
        [
          8.0,
          348.0
        ],
        [
          24.0,
          339.0
        ],
        [
          26.0,
          339.0
        ],
        [
          31.0,
          334.0
        ],
        [
          23.0,
          303.0
        ],
        [
          23.0,
          293.0
        ],
        [
          21.0,
          284.0
        ],
        [
          21.0,
          249.0
        ],
        [
          22.0,
          248.0
        ],
        [
          25.0,
          224.0
        ],
        [
          27.0,
          221.0
        ],
        [
          30.0,
          206.0
        ],
        [
          37.0,
          188.0
        ],
        [
          53.0,
          156.0
        ],
        [
          68.0,
          134.0
        ],
        [
          89.0,
          109.0
        ],
        [
          95.0,
          104.0
        ],
        [
          108.0,
          89.0
        ],
        [
          97.0,
          72.0
        ],
        [
          75.0,
          45.0
        ],
        [
          68.0,
          34.0
        ],
        [
          64.0,
          31.0
        ],
        [
          60.0,
          24.0
        ],
        [
          55.0,
          21.0
        ],
        [
          55.0,
          19.0
        ],
        [
          40.0,
          16.0
        ],
        [
          17.0,
          14.0
        ],
        [
          15.0,
          12.0
        ],
        [
          11.0,
          12.0
        ]
      ],
      "group_id": null,
      "description": "",
      "difficult": false,
      "shape_type": "polygon",
      "flags": {},
      "attributes": {},
      "kie_linking": []
    },
    {
      "label": "Healthy_Apple",
      "score": null,
      "points": [
        [
          93.0,
          14.0
        ],
        [
          96.0,
          16.0
        ],
        [
          96.0,
          23.0
        ],
        [
          98.0,
          29.0
        ],
        [
          103.0,
          33.0
        ],
        [
          102.0,
          35.0
        ],
        [
          108.0,
          41.0
        ],
        [
          108.0,
          46.0
        ],
        [
          116.0,
          54.0
        ],
        [
          117.0,
          58.0
        ],
        [
          123.0,
          64.0
        ],
        [
          126.0,
          70.0
        ],
        [
          130.0,
          70.0
        ],
        [
          147.0,
          56.0
        ],
        [
          150.0,
          55.0
        ],
        [
          159.0,
          48.0
        ],
        [
          167.0,
          44.0
        ],
        [
          172.0,
          40.0
        ],
        [
          174.0,
          40.0
        ],
        [
          190.0,
          32.0
        ],
        [
          195.0,
          31.0
        ],
        [
          210.0,
          24.0
        ],
        [
          217.0,
          23.0
        ],
        [
          221.0,
          21.0
        ],
        [
          241.0,
          19.0
        ],
        [
          242.0,
          18.0
        ],
        [
          255.0,
          18.0
        ],
        [
          256.0,
          17.0
        ],
        [
          284.0,
          18.0
        ],
        [
          285.0,
          19.0
        ],
        [
          299.0,
          20.0
        ],
        [
          318.0,
          24.0
        ],
        [
          353.0,
          36.0
        ],
        [
          383.0,
          51.0
        ],
        [
          385.0,
          53.0
        ],
        [
          393.0,
          54.0
        ],
        [
          399.0,
          46.0
        ],
        [
          410.0,
          27.0
        ],
        [
          416.0,
          12.0
        ],
        [
          419.0,
          0.0
        ],
        [
          96.0,
          0.0
        ],
        [
          96.0,
          3.0
        ],
        [
          93.0,
          6.0
        ],
        [
          94.0,
          8.0
        ]
      ],
      "group_id": null,
      "description": "",
      "difficult": false,
      "shape_type": "polygon",
      "flags": {},
      "attributes": {},
      "kie_linking": []
    },
    {
      "label": "Anthracnose",
      "score": null,
      "points": [
        [
          396.0,
          249.0
        ],
        [
          395.0,
          249.0
        ],
        [
          394.0,
          248.0
        ],
        [
          392.0,
          248.0
        ],
        [
          391.0,
          247.0
        ],
        [
          388.0,
          247.0
        ],
        [
          387.0,
          246.0
        ],
        [
          384.0,
          246.0
        ],
        [
          383.0,
          245.0
        ],
        [
          381.0,
          245.0
        ],
        [
          380.0,
          244.0
        ],
        [
          378.0,
          244.0
        ],
        [
          377.0,
          243.0
        ],
        [
          375.0,
          243.0
        ],
        [
          374.0,
          242.0
        ],
        [
          371.0,
          242.0
        ],
        [
          370.0,
          241.0
        ],
        [
          366.0,
          241.0
        ],
        [
          365.0,
          240.0
        ],
        [
          364.0,
          240.0
        ],
        [
          363.0,
          241.0
        ],
        [
          351.0,
          241.0
        ],
        [
          350.0,
          242.0
        ],
        [
          348.0,
          242.0
        ],
        [
          347.0,
          243.0
        ],
        [
          345.0,
          243.0
        ],
        [
          344.0,
          244.0
        ],
        [
          341.0,
          244.0
        ],
        [
          340.0,
          245.0
        ],
        [
          336.0,
          245.0
        ],
        [
          331.0,
          248.0
        ],
        [
          331.0,
          249.0
        ],
        [
          323.0,
          258.0
        ],
        [
          323.0,
          259.0
        ],
        [
          321.0,
          261.0
        ],
        [
          320.0,
          264.0
        ],
        [
          314.0,
          271.0
        ],
        [
          314.0,
          272.0
        ],
        [
          311.0,
          277.0
        ],
        [
          312.0,
          278.0
        ],
        [
          312.0,
          279.0
        ],
        [
          311.0,
          280.0
        ],
        [
          311.0,
          284.0
        ],
        [
          310.0,
          285.0
        ],
        [
          310.0,
          290.0
        ],
        [
          307.0,
          295.0
        ],
        [
          307.0,
          298.0
        ],
        [
          306.0,
          299.0
        ],
        [
          306.0,
          307.0
        ],
        [
          307.0,
          308.0
        ],
        [
          307.0,
          311.0
        ],
        [
          308.0,
          312.0
        ],
        [
          308.0,
          315.0
        ],
        [
          309.0,
          316.0
        ],
        [
          309.0,
          319.0
        ],
        [
          310.0,
          320.0
        ],
        [
          310.0,
          323.0
        ],
        [
          311.0,
          324.0
        ],
        [
          311.0,
          327.0
        ],
        [
          312.0,
          328.0
        ],
        [
          312.0,
          330.0
        ],
        [
          314.0,
          332.0
        ],
        [
          314.0,
          333.0
        ],
        [
          315.0,
          334.0
        ],
        [
          315.0,
          336.0
        ],
        [
          316.0,
          337.0
        ],
        [
          316.0,
          338.0
        ],
        [
          319.0,
          341.0
        ],
        [
          320.0,
          341.0
        ],
        [
          322.0,
          343.0
        ],
        [
          323.0,
          343.0
        ],
        [
          328.0,
          346.0
        ],
        [
          331.0,
          346.0
        ],
        [
          332.0,
          347.0
        ],
        [
          340.0,
          347.0
        ],
        [
          341.0,
          348.0
        ],
        [
          353.0,
          348.0
        ],
        [
          354.0,
          349.0
        ],
        [
          355.0,
          349.0
        ],
        [
          356.0,
          348.0
        ],
        [
          364.0,
          348.0
        ],
        [
          365.0,
          347.0
        ],
        [
          369.0,
          347.0
        ],
        [
          374.0,
          344.0
        ],
        [
          376.0,
          344.0
        ],
        [
          377.0,
          343.0
        ],
        [
          380.0,
          343.0
        ],
        [
          381.0,
          342.0
        ],
        [
          383.0,
          342.0
        ],
        [
          384.0,
          341.0
        ],
        [
          386.0,
          341.0
        ],
        [
          388.0,
          339.0
        ],
        [
          389.0,
          339.0
        ],
        [
          407.0,
          321.0
        ],
        [
          407.0,
          319.0
        ],
        [
          408.0,
          318.0
        ],
        [
          408.0,
          317.0
        ],
        [
          410.0,
          315.0
        ],
        [
          410.0,
          313.0
        ],
        [
          412.0,
          310.0
        ],
        [
          412.0,
          305.0
        ],
        [
          413.0,
          304.0
        ],
        [
          413.0,
          302.0
        ],
        [
          412.0,
          301.0
        ],
        [
          412.0,
          295.0
        ],
        [
          411.0,
          294.0
        ],
        [
          411.0,
          291.0
        ],
        [
          412.0,
          290.0
        ],
        [
          412.0,
          275.0
        ],
        [
          411.0,
          274.0
        ],
        [
          411.0,
          271.0
        ],
        [
          410.0,
          270.0
        ],
        [
          410.0,
          268.0
        ],
        [
          408.0,
          266.0
        ],
        [
          408.0,
          264.0
        ],
        [
          407.0,
          263.0
        ],
        [
          407.0,
          262.0
        ],
        [
          406.0,
          261.0
        ],
        [
          406.0,
          260.0
        ],
        [
          405.0,
          259.0
        ],
        [
          404.0,
          256.0
        ],
        [
          401.0,
          253.0
        ],
        [
          400.0,
          253.0
        ]
      ],
      "group_id": null,
      "description": "",
      "difficult": false,
      "shape_type": "polygon",
      "flags": {},
      "attributes": {},
      "kie_linking": []
    },
    {
      "label": "Anthracnose",
      "score": null,
      "points": [
        [
          242.0,
          102.0
        ],
        [
          240.0,
          102.0
        ],
        [
          239.0,
          101.0
        ],
        [
          238.0,
          101.0
        ],
        [
          237.0,
          100.0
        ],
        [
          235.0,
          100.0
        ],
        [
          234.0,
          99.0
        ],
        [
          231.0,
          99.0
        ],
        [
          230.0,
          98.0
        ],
        [
          227.0,
          98.0
        ],
        [
          226.0,
          97.0
        ],
        [
          220.0,
          97.0
        ],
        [
          219.0,
          96.0
        ],
        [
          216.0,
          96.0
        ],
        [
          215.0,
          97.0
        ],
        [
          212.0,
          97.0
        ],
        [
          211.0,
          98.0
        ],
        [
          207.0,
          98.0
        ],
        [
          206.0,
          99.0
        ],
        [
          202.0,
          99.0
        ],
        [
          201.0,
          100.0
        ],
        [
          197.0,
          100.0
        ],
        [
          196.0,
          101.0
        ],
        [
          195.0,
          101.0
        ],
        [
          193.0,
          103.0
        ],
        [
          192.0,
          103.0
        ],
        [
          191.0,
          104.0
        ],
        [
          190.0,
          104.0
        ],
        [
          187.0,
          107.0
        ],
        [
          186.0,
          107.0
        ],
        [
          185.0,
          108.0
        ],
        [
          184.0,
          108.0
        ],
        [
          182.0,
          110.0
        ],
        [
          181.0,
          110.0
        ],
        [
          179.0,
          112.0
        ],
        [
          178.0,
          112.0
        ],
        [
          176.0,
          114.0
        ],
        [
          176.0,
          115.0
        ],
        [
          174.0,
          117.0
        ],
        [
          174.0,
          119.0
        ],
        [
          173.0,
          120.0
        ],
        [
          173.0,
          121.0
        ],
        [
          172.0,
          122.0
        ],
        [
          172.0,
          123.0
        ],
        [
          170.0,
          125.0
        ],
        [
          170.0,
          127.0
        ],
        [
          169.0,
          128.0
        ],
        [
          169.0,
          130.0
        ],
        [
          168.0,
          131.0
        ],
        [
          168.0,
          151.0
        ],
        [
          169.0,
          152.0
        ],
        [
          169.0,
          155.0
        ],
        [
          170.0,
          156.0
        ],
        [
          170.0,
          159.0
        ],
        [
          171.0,
          160.0
        ],
        [
          171.0,
          161.0
        ],
        [
          172.0,
          162.0
        ],
        [
          172.0,
          163.0
        ],
        [
          176.0,
          167.0
        ],
        [
          177.0,
          167.0
        ],
        [
          179.0,
          169.0
        ],
        [
          180.0,
          169.0
        ],
        [
          181.0,
          170.0
        ],
        [
          182.0,
          170.0
        ],
        [
          184.0,
          172.0
        ],
        [
          185.0,
          172.0
        ],
        [
          186.0,
          173.0
        ],
        [
          188.0,
          173.0
        ],
        [
          189.0,
          174.0
        ],
        [
          190.0,
          174.0
        ],
        [
          191.0,
          175.0
        ],
        [
          192.0,
          175.0
        ],
        [
          195.0,
          177.0
        ],
        [
          197.0,
          177.0
        ],
        [
          198.0,
          178.0
        ],
        [
          200.0,
          178.0
        ],
        [
          201.0,
          179.0
        ],
        [
          220.0,
          179.0
        ],
        [
          221.0,
          178.0
        ],
        [
          223.0,
          178.0
        ],
        [
          224.0,
          177.0
        ],
        [
          226.0,
          177.0
        ],
        [
          227.0,
          176.0
        ],
        [
          229.0,
          176.0
        ],
        [
          230.0,
          175.0
        ],
        [
          232.0,
          175.0
        ],
        [
          233.0,
          174.0
        ],
        [
          234.0,
          174.0
        ],
        [
          235.0,
          173.0
        ],
        [
          236.0,
          173.0
        ],
        [
          237.0,
          172.0
        ],
        [
          238.0,
          172.0
        ],
        [
          239.0,
          171.0
        ],
        [
          240.0,
          171.0
        ],
        [
          242.0,
          169.0
        ],
        [
          243.0,
          169.0
        ],
        [
          247.0,
          165.0
        ],
        [
          247.0,
          164.0
        ],
        [
          249.0,
          162.0
        ],
        [
          250.0,
          162.0
        ],
        [
          250.0,
          161.0
        ],
        [
          251.0,
          160.0
        ],
        [
          251.0,
          159.0
        ],
        [
          252.0,
          158.0
        ],
        [
          252.0,
          157.0
        ],
        [
          253.0,
          156.0
        ],
        [
          253.0,
          155.0
        ],
        [
          255.0,
          152.0
        ],
        [
          255.0,
          150.0
        ],
        [
          257.0,
          148.0
        ],
        [
          257.0,
          147.0
        ],
        [
          259.0,
          145.0
        ],
        [
          259.0,
          144.0
        ],
        [
          261.0,
          142.0
        ],
        [
          261.0,
          141.0
        ],
        [
          262.0,
          140.0
        ],
        [
          262.0,
          136.0
        ],
        [
          263.0,
          135.0
        ],
        [
          263.0,
          131.0
        ],
        [
          262.0,
          130.0
        ],
        [
          262.0,
          127.0
        ],
        [
          261.0,
          126.0
        ],
        [
          261.0,
          124.0
        ],
        [
          260.0,
          123.0
        ],
        [
          260.0,
          122.0
        ],
        [
          259.0,
          121.0
        ],
        [
          259.0,
          120.0
        ],
        [
          254.0,
          115.0
        ],
        [
          254.0,
          114.0
        ],
        [
          247.0,
          107.0
        ],
        [
          247.0,
          106.0
        ],
        [
          245.0,
          104.0
        ],
        [
          244.0,
          104.0
        ]
      ],
      "group_id": null,
      "description": "",
      "difficult": false,
      "shape_type": "polygon",
      "flags": {},
      "attributes": {},
      "kie_linking": []
    },
    {
      "label": "Anthracnose",
      "score": null,
      "points": [
        [
          51.0,
          202.0
        ],
        [
          46.0,
          202.0
        ],
        [
          40.0,
          208.0
        ],
        [
          40.0,
          209.0
        ],
        [
          38.0,
          211.0
        ],
        [
          38.0,
          212.0
        ],
        [
          37.0,
          213.0
        ],
        [
          37.0,
          215.0
        ],
        [
          36.0,
          216.0
        ],
        [
          36.0,
          218.0
        ],
        [
          35.0,
          219.0
        ],
        [
          35.0,
          222.0
        ],
        [
          34.0,
          223.0
        ],
        [
          34.0,
          225.0
        ],
        [
          33.0,
          226.0
        ],
        [
          33.0,
          228.0
        ],
        [
          32.0,
          229.0
        ],
        [
          32.0,
          232.0
        ],
        [
          31.0,
          233.0
        ],
        [
          31.0,
          239.0
        ],
        [
          30.0,
          240.0
        ],
        [
          30.0,
          268.0
        ],
        [
          31.0,
          269.0
        ],
        [
          31.0,
          274.0
        ],
        [
          32.0,
          275.0
        ],
        [
          32.0,
          277.0
        ],
        [
          33.0,
          278.0
        ],
        [
          33.0,
          280.0
        ],
        [
          34.0,
          281.0
        ],
        [
          34.0,
          282.0
        ],
        [
          35.0,
          283.0
        ],
        [
          35.0,
          284.0
        ],
        [
          36.0,
          285.0
        ],
        [
          36.0,
          286.0
        ],
        [
          37.0,
          287.0
        ],
        [
          37.0,
          288.0
        ],
        [
          42.0,
          293.0
        ],
        [
          44.0,
          293.0
        ],
        [
          45.0,
          294.0
        ],
        [
          46.0,
          294.0
        ],
        [
          47.0,
          293.0
        ],
        [
          50.0,
          293.0
        ],
        [
          51.0,
          292.0
        ],
        [
          52.0,
          292.0
        ],
        [
          54.0,
          290.0
        ],
        [
          54.0,
          289.0
        ],
        [
          55.0,
          288.0
        ],
        [
          55.0,
          287.0
        ],
        [
          57.0,
          285.0
        ],
        [
          57.0,
          282.0
        ],
        [
          58.0,
          281.0
        ],
        [
          58.0,
          277.0
        ],
        [
          59.0,
          276.0
        ],
        [
          59.0,
          270.0
        ],
        [
          60.0,
          269.0
        ],
        [
          60.0,
          263.0
        ],
        [
          61.0,
          262.0
        ],
        [
          61.0,
          256.0
        ],
        [
          62.0,
          255.0
        ],
        [
          62.0,
          239.0
        ],
        [
          61.0,
          238.0
        ],
        [
          61.0,
          228.0
        ],
        [
          60.0,
          227.0
        ],
        [
          60.0,
          224.0
        ],
        [
          59.0,
          223.0
        ],
        [
          59.0,
          220.0
        ],
        [
          58.0,
          219.0
        ],
        [
          58.0,
          216.0
        ],
        [
          57.0,
          215.0
        ],
        [
          57.0,
          212.0
        ],
        [
          56.0,
          211.0
        ],
        [
          56.0,
          210.0
        ],
        [
          55.0,
          209.0
        ],
        [
          55.0,
          207.0
        ],
        [
          54.0,
          206.0
        ],
        [
          54.0,
          205.0
        ]
      ],
      "group_id": null,
      "description": "",
      "difficult": false,
      "shape_type": "polygon",
      "flags": {},
      "attributes": {},
      "kie_linking": []
    },
    {
      "label": "Anthracnose",
      "score": null,
      "points": [
        [
          472.0,
          179.0
        ],
        [
          472.0,
          186.0
        ],
        [
          473.0,
          187.0
        ],
        [
          473.0,
          192.0
        ],
        [
          474.0,
          193.0
        ],
        [
          474.0,
          201.0
        ],
        [
          475.0,
          202.0
        ],
        [
          475.0,
          203.0
        ],
        [
          476.0,
          204.0
        ],
        [
          476.0,
          205.0
        ],
        [
          479.0,
          205.0
        ],
        [
          480.0,
          204.0
        ],
        [
          480.0,
          199.0
        ],
        [
          479.0,
          198.0
        ],
        [
          479.0,
          188.0
        ],
        [
          478.0,
          187.0
        ],
        [
          478.0,
          186.0
        ],
        [
          477.0,
          185.0
        ],
        [
          477.0,
          184.0
        ],
        [
          476.0,
          183.0
        ],
        [
          476.0,
          182.0
        ],
        [
          473.0,
          179.0
        ]
      ],
      "group_id": null,
      "description": "",
      "difficult": false,
      "shape_type": "polygon",
      "flags": {},
      "attributes": {},
      "kie_linking": []
    }
  ],
  "imagePath": "anthracnose_0244.jpg",
  "imageData": null,
  "imageHeight": 512,
  "imageWidth": 512
}