{
  "version": "3.3.10",
  "flags": {},
  "shapes": [
    {
      "label": "Healthy_Apple",
      "score": null,
      "points": [
        [
          260.0,
          5.0
        ],
        [
          206.0,
          10.0
        ],
        [
          181.0,
          16.0
        ],
        [
          145.0,
          31.0
        ],
        [
          110.0,
          55.0
        ],
        [
          72.0,
          95.0
        ],
        [
          56.0,
          117.0
        ],
        [
          47.0,
          136.0
        ],
        [
          32.0,
          185.0
        ],
        [
          25.0,
          247.0
        ],
        [
          28.0,
          307.0
        ],
        [
          24.0,
          311.0
        ],
        [
          29.0,
          310.0
        ],
        [
          31.0,
          312.0
        ],
        [
          33.0,
          329.0
        ],
        [
          39.0,
          344.0
        ],
        [
          39.0,
          353.0
        ],
        [
          58.0,
          393.0
        ],
        [
          82.0,
          426.0
        ],
        [
          111.0,
          455.0
        ],
        [
          133.0,
          471.0
        ],
        [
          189.0,
          496.0
        ],
        [
          252.0,
          507.0
        ],
        [
          273.0,
          507.0
        ],
        [
          315.0,
          499.0
        ],
        [
          367.0,
          475.0
        ],
        [
          416.0,
          439.0
        ],
        [
          440.0,
          413.0
        ],
        [
          464.0,
          374.0
        ],
        [
          479.0,
          334.0
        ],
        [
          487.0,
          281.0
        ],
        [
          487.0,
          228.0
        ],
        [
          480.0,
          173.0
        ],
        [
          466.0,
          136.0
        ],
        [
          448.0,
          107.0
        ],
        [
          414.0,
          71.0
        ],
        [
          376.0,
          40.0
        ],
        [
          330.0,
          16.0
        ],
        [
          302.0,
          8.0
        ]
      ],
      "group_id": null,
      "description": "",
      "difficult": false,
      "shape_type": "polygon",
      "flags": {},
      "attributes": {},
      "kie_linking": []
    },
    {
      "label": "Black_Rot",
      "score": null,
      "points": [
        [
          221.0,
          193.0
        ],
        [
          220.0,
          194.0
        ],
        [
          219.0,
          194.0
        ],
        [
          217.0,
          196.0
        ],
        [
          215.0,
          196.0
        ],
        [
          214.0,
          197.0
        ],
        [
          213.0,
          197.0
        ],
        [
          213.0,
          198.0
        ],
        [
          212.0,
          199.0
        ],
        [
          212.0,
          201.0
        ],
        [
          211.0,
          202.0
        ],
        [
          211.0,
          203.0
        ],
        [
          210.0,
          204.0
        ],
        [
          210.0,
          206.0
        ],
        [
          209.0,
          207.0
        ],
        [
          209.0,
          210.0
        ],
        [
          208.0,
          211.0
        ],
        [
          208.0,
          212.0
        ],
        [
          209.0,
          213.0
        ],
        [
          209.0,
          219.0
        ],
        [
          210.0,
          220.0
        ],
        [
          210.0,
          221.0
        ],
        [
          211.0,
          222.0
        ],
        [
          211.0,
          223.0
        ],
        [
          212.0,
          224.0
        ],
        [
          212.0,
          228.0
        ],
        [
          211.0,
          229.0
        ],
        [
          211.0,
          231.0
        ],
        [
          210.0,
          232.0
        ],
        [
          210.0,
          235.0
        ],
        [
          209.0,
          236.0
        ],
        [
          209.0,
          244.0
        ],
        [
          210.0,
          245.0
        ],
        [
          210.0,
          247.0
        ],
        [
          211.0,
          248.0
        ],
        [
          211.0,
          250.0
        ],
        [
          212.0,
          251.0
        ],
        [
          212.0,
          252.0
        ],
        [
          213.0,
          253.0
        ],
        [
          213.0,
          254.0
        ],
        [
          214.0,
          255.0
        ],
        [
          214.0,
          256.0
        ],
        [
          215.0,
          257.0
        ],
        [
          215.0,
          258.0
        ],
        [
          216.0,
          259.0
        ],
        [
          216.0,
          260.0
        ],
        [
          217.0,
          261.0
        ],
        [
          217.0,
          262.0
        ],
        [
          218.0,
          263.0
        ],
        [
          218.0,
          266.0
        ],
        [
          220.0,
          268.0
        ],
        [
          220.0,
          269.0
        ],
        [
          222.0,
          271.0
        ],
        [
          222.0,
          272.0
        ],
        [
          226.0,
          276.0
        ],
        [
          227.0,
          276.0
        ],
        [
          229.0,
          278.0
        ],
        [
          230.0,
          278.0
        ],
        [
          231.0,
          279.0
        ],
        [
          232.0,
          279.0
        ],
        [
          235.0,
          282.0
        ],
        [
          236.0,
          282.0
        ],
        [
          237.0,
          283.0
        ],
        [
          239.0,
          283.0
        ],
        [
          240.0,
          284.0
        ],
        [
          248.0,
          284.0
        ],
        [
          249.0,
          283.0
        ],
        [
          250.0,
          283.0
        ],
        [
          251.0,
          282.0
        ],
        [
          252.0,
          282.0
        ],
        [
          257.0,
          277.0
        ],
        [
          257.0,
          276.0
        ],
        [
          258.0,
          275.0
        ],
        [
          258.0,
          274.0
        ],
        [
          259.0,
          273.0
        ],
        [
          259.0,
          272.0
        ],
        [
          260.0,
          271.0
        ],
        [
          260.0,
          270.0
        ],
        [
          263.0,
          267.0
        ],
        [
          263.0,
          266.0
        ],
        [
          264.0,
          265.0
        ],
        [
          264.0,
          264.0
        ],
        [
          267.0,
          261.0
        ],
        [
          267.0,
          260.0
        ],
        [
          270.0,
          257.0
        ],
        [
          270.0,
          256.0
        ],
        [
          273.0,
          253.0
        ],
        [
          273.0,
          252.0
        ],
        [
          274.0,
          251.0
        ],
        [
          274.0,
          250.0
        ],
        [
          275.0,
          249.0
        ],
        [
          275.0,
          247.0
        ],
        [
          276.0,
          246.0
        ],
        [
          276.0,
          244.0
        ],
        [
          277.0,
          243.0
        ],
        [
          277.0,
          221.0
        ],
        [
          276.0,
          220.0
        ],
        [
          276.0,
          218.0
        ],
        [
          275.0,
          217.0
        ],
        [
          275.0,
          216.0
        ],
        [
          272.0,
          213.0
        ],
        [
          272.0,
          212.0
        ],
        [
          270.0,
          210.0
        ],
        [
          270.0,
          209.0
        ],
        [
          267.0,
          206.0
        ],
        [
          267.0,
          205.0
        ],
        [
          266.0,
          204.0
        ],
        [
          266.0,
          203.0
        ],
        [
          264.0,
          201.0
        ],
        [
          264.0,
          200.0
        ],
        [
          261.0,
          197.0
        ],
        [
          260.0,
          197.0
        ],
        [
          259.0,
          196.0
        ],
        [
          257.0,
          196.0
        ],
        [
          256.0,
          195.0
        ],
        [
          252.0,
          195.0
        ],
        [
          251.0,
          194.0
        ],
        [
          234.0,
          194.0
        ],
        [
          233.0,
          193.0
        ],
        [
          232.0,
          193.0
        ],
        [
          231.0,
          194.0
        ],
        [
          224.0,
          194.0
        ],
        [
          223.0,
          193.0
        ]
      ],
      "group_id": null,
      "description": null,
      "difficult": false,
      "shape_type": "polygon",
      "flags": {},
      "attributes": {},
      "kie_linking": []
    },
    {
      "label": "Black_Rot",
      "score": null,
      "points": [
        [
          138.0,
          169.0
        ],
        [
          136.0,
          169.0
        ],
        [
          135.0,
          168.0
        ],
        [
          131.0,
          168.0
        ],
        [
          130.0,
          169.0
        ],
        [
          125.0,
          169.0
        ],
        [
          124.0,
          170.0
        ],
        [
          122.0,
          170.0
        ],
        [
          121.0,
          171.0
        ],
        [
          119.0,
          171.0
        ],
        [
          118.0,
          172.0
        ],
        [
          116.0,
          172.0
        ],
        [
          108.0,
          180.0
        ],
        [
          108.0,
          182.0
        ],
        [
          107.0,
          183.0
        ],
        [
          107.0,
          186.0
        ],
        [
          106.0,
          187.0
        ],
        [
          106.0,
          201.0
        ],
        [
          107.0,
          202.0
        ],
        [
          107.0,
          206.0
        ],
        [
          108.0,
          207.0
        ],
        [
          108.0,
          209.0
        ],
        [
          111.0,
          212.0
        ],
        [
          113.0,
          212.0
        ],
        [
          115.0,
          214.0
        ],
        [
          116.0,
          213.0
        ],
        [
          117.0,
          213.0
        ],
        [
          119.0,
          215.0
        ],
        [
          120.0,
          214.0
        ],
        [
          121.0,
          214.0
        ],
        [
          122.0,
          215.0
        ],
        [
          124.0,
          215.0
        ],
        [
          125.0,
          214.0
        ],
        [
          127.0,
          214.0
        ],
        [
          128.0,
          213.0
        ],
        [
          129.0,
          213.0
        ],
        [
          130.0,
          214.0
        ],
        [
          130.0,
          213.0
        ],
        [
          131.0,
          212.0
        ],
        [
          132.0,
          212.0
        ],
        [
          133.0,
          211.0
        ],
        [
          134.0,
          211.0
        ],
        [
          136.0,
          209.0
        ],
        [
          137.0,
          209.0
        ],
        [
          137.0,
          208.0
        ],
        [
          138.0,
          207.0
        ],
        [
          139.0,
          207.0
        ],
        [
          139.0,
          206.0
        ],
        [
          145.0,
          200.0
        ],
        [
          145.0,
          199.0
        ],
        [
          146.0,
          198.0
        ],
        [
          146.0,
          197.0
        ],
        [
          147.0,
          196.0
        ],
        [
          147.0,
          195.0
        ],
        [
          148.0,
          194.0
        ],
        [
          148.0,
          190.0
        ],
        [
          149.0,
          189.0
        ],
        [
          149.0,
          187.0
        ],
        [
          148.0,
          186.0
        ],
        [
          148.0,
          181.0
        ],
        [
          147.0,
          180.0
        ],
        [
          147.0,
          179.0
        ],
        [
          145.0,
          177.0
        ],
        [
          145.0,
          176.0
        ]
      ],
      "group_id": null,
      "description": null,
      "difficult": false,
      "shape_type": "polygon",
      "flags": {},
      "attributes": {},
      "kie_linking": []
    },
    {
      "label": "Black_Rot",
      "score": null,
      "points": [
        [
          60.0,
          166.0
        ],
        [
          58.0,
          166.0
        ],
        [
          54.0,
          170.0
        ],
        [
          54.0,
          171.0
        ],
        [
          52.0,
          173.0
        ],
        [
          52.0,
          177.0
        ],
        [
          51.0,
          178.0
        ],
        [
          51.0,
          180.0
        ],
        [
          52.0,
          181.0
        ],
        [
          52.0,
          184.0
        ],
        [
          53.0,
          185.0
        ],
        [
          55.0,
          185.0
        ],
        [
          55.0,
          184.0
        ],
        [
          56.0,
          183.0
        ],
        [
          56.0,
          182.0
        ],
        [
          57.0,
          181.0
        ],
        [
          57.0,
          180.0
        ],
        [
          59.0,
          178.0
        ],
        [
          59.0,
          176.0
        ],
        [
          60.0,
          175.0
        ],
        [
          60.0,
          172.0
        ],
        [
          61.0,
          171.0
        ],
        [
          61.0,
          167.0
        ]
      ],
      "group_id": null,
      "description": null,
      "difficult": false,
      "shape_type": "polygon",
      "flags": {},
      "attributes": {},
      "kie_linking": []
    },
    {
      "label": "Black_Rot",
      "score": null,
      "points": [
        [
          48.0,
          284.0
        ],
        [
          48.0,
          285.0
        ],
        [
          47.0,
          286.0
        ],
        [
          47.0,
          292.0
        ],
        [
          48.0,
          293.0
        ],
        [
          48.0,
          296.0
        ],
        [
          49.0,
          297.0
        ],
        [
          49.0,
          299.0
        ],
        [
          50.0,
          300.0
        ],
        [
          50.0,
          301.0
        ],
        [
          52.0,
          303.0
        ],
        [
          53.0,
          303.0
        ],
        [
          55.0,
          301.0
        ],
        [
          55.0,
          298.0
        ],
        [
          54.0,
          297.0
        ],
        [
          54.0,
          294.0
        ],
        [
          53.0,
          293.0
        ],
        [
          53.0,
          291.0
        ],
        [
          52.0,
          290.0
        ],
        [
          52.0,
          288.0
        ],
        [
          51.0,
          287.0
        ],
        [
          51.0,
          286.0
        ],
        [
          49.0,
          284.0
        ]
      ],
      "group_id": null,
      "description": null,
      "difficult": false,
      "shape_type": "polygon",
      "flags": {},
      "attributes": {},
      "kie_linking": []
    },
    {
      "label": "Black_Rot",
      "score": null,
      "points": [
        [
          106.0,
          318.0
        ],
        [
          106.0,
          319.0
        ],
        [
          104.0,
          321.0
        ],
        [
          104.0,
          322.0
        ],
        [
          101.0,
          325.0
        ],
        [
          100.0,
          328.0
        ],
        [
          97.0,
          331.0
        ],
        [
          97.0,
          332.0
        ],
        [
          96.0,
          333.0
        ],
        [
          96.0,
          335.0
        ],
        [
          95.0,
          336.0
        ],
        [
          95.0,
          347.0
        ],
        [
          96.0,
          348.0
        ],
        [
          96.0,
          351.0
        ],
        [
          98.0,
          354.0
        ],
        [
          98.0,
          356.0
        ],
        [
          99.0,
          357.0
        ],
        [
          99.0,
          358.0
        ],
        [
          100.0,
          359.0
        ],
        [
          100.0,
          360.0
        ],
        [
          101.0,
          361.0
        ],
        [
          101.0,
          362.0
        ],
        [
          102.0,
          363.0
        ],
        [
          102.0,
          364.0
        ],
        [
          104.0,
          367.0
        ],
        [
          104.0,
          369.0
        ],
        [
          109.0,
          374.0
        ],
        [
          110.0,
          374.0
        ],
        [
          111.0,
          375.0
        ],
        [
          111.0,
          376.0
        ],
        [
          115.0,
          380.0
        ],
        [
          116.0,
          380.0
        ],
        [
          118.0,
          382.0
        ],
        [
          119.0,
          382.0
        ],
        [
          121.0,
          384.0
        ],
        [
          122.0,
          384.0
        ],
        [
          125.0,
          386.0
        ],
        [
          127.0,
          386.0
        ],
        [
          130.0,
          388.0
        ],
        [
          135.0,
          388.0
        ],
        [
          136.0,
          389.0
        ],
        [
          153.0,
          389.0
        ],
        [
          154.0,
          390.0
        ],
        [
          163.0,
          390.0
        ],
        [
          164.0,
          391.0
        ],
        [
          165.0,
          391.0
        ],
        [
          166.0,
          390.0
        ],
        [
          171.0,
          390.0
        ],
        [
          172.0,
          391.0
        ],
        [
          180.0,
          391.0
        ],
        [
          181.0,
          392.0
        ],
        [
          185.0,
          392.0
        ],
        [
          186.0,
          391.0
        ],
        [
          190.0,
          391.0
        ],
        [
          193.0,
          388.0
        ],
        [
          193.0,
          387.0
        ],
        [
          195.0,
          384.0
        ],
        [
          195.0,
          382.0
        ],
        [
          196.0,
          381.0
        ],
        [
          196.0,
          361.0
        ],
        [
          195.0,
          360.0
        ],
        [
          195.0,
          356.0
        ],
        [
          194.0,
          355.0
        ],
        [
          194.0,
          353.0
        ],
        [
          192.0,
          350.0
        ],
        [
          192.0,
          344.0
        ],
        [
          191.0,
          343.0
        ],
        [
          191.0,
          339.0
        ],
        [
          190.0,
          338.0
        ],
        [
          190.0,
          336.0
        ],
        [
          186.0,
          332.0
        ],
        [
          183.0,
          331.0
        ],
        [
          181.0,
          329.0
        ],
        [
          181.0,
          328.0
        ],
        [
          177.0,
          324.0
        ],
        [
          177.0,
          323.0
        ],
        [
          176.0,
          323.0
        ],
        [
          171.0,
          318.0
        ],
        [
          168.0,
          317.0
        ],
        [
          166.0,
          315.0
        ],
        [
          165.0,
          315.0
        ],
        [
          164.0,
          314.0
        ],
        [
          161.0,
          314.0
        ],
        [
          160.0,
          313.0
        ],
        [
          159.0,
          314.0
        ],
        [
          158.0,
          314.0
        ],
        [
          157.0,
          313.0
        ],
        [
          154.0,
          313.0
        ],
        [
          153.0,
          312.0
        ],
        [
          152.0,
          312.0
        ],
        [
          150.0,
          310.0
        ],
        [
          143.0,
          310.0
        ],
        [
          142.0,
          311.0
        ],
        [
          140.0,
          311.0
        ],
        [
          137.0,
          314.0
        ],
        [
          136.0,
          314.0
        ],
        [
          134.0,
          316.0
        ],
        [
          132.0,
          316.0
        ],
        [
          129.0,
          314.0
        ],
        [
          127.0,
          314.0
        ],
        [
          125.0,
          312.0
        ],
        [
          124.0,
          312.0
        ],
        [
          123.0,
          311.0
        ],
        [
          122.0,
          311.0
        ],
        [
          121.0,
          312.0
        ],
        [
          120.0,
          312.0
        ],
        [
          119.0,
          311.0
        ],
        [
          117.0,
          311.0
        ],
        [
          116.0,
          312.0
        ],
        [
          113.0,
          312.0
        ],
        [
          112.0,
          313.0
        ],
        [
          111.0,
          313.0
        ]
      ],
      "group_id": null,
      "description": null,
      "difficult": false,
      "shape_type": "polygon",
      "flags": {},
      "attributes": {},
      "kie_linking": []
    },
    {
      "label": "Black_Rot",
      "score": null,
      "points": [
        [
          66.0,
          361.0
        ],
        [
          65.0,
          362.0
        ],
        [
          65.0,
          363.0
        ],
        [
          64.0,
          364.0
        ],
        [
          64.0,
          366.0
        ],
        [
          63.0,
          367.0
        ],
        [
          63.0,
          368.0
        ],
        [
          62.0,
          369.0
        ],
        [
          62.0,
          370.0
        ],
        [
          61.0,
          371.0
        ],
        [
          61.0,
          375.0
        ],
        [
          62.0,
          376.0
        ],
        [
          62.0,
          378.0
        ],
        [
          63.0,
          379.0
        ],
        [
          63.0,
          381.0
        ],
        [
          64.0,
          382.0
        ],
        [
          64.0,
          385.0
        ],
        [
          65.0,
          386.0
        ],
        [
          65.0,
          387.0
        ],
        [
          66.0,
          388.0
        ],
        [
          66.0,
          389.0
        ],
        [
          67.0,
          390.0
        ],
        [
          67.0,
          391.0
        ],
        [
          68.0,
          392.0
        ],
        [
          68.0,
          393.0
        ],
        [
          69.0,
          394.0
        ],
        [
          69.0,
          395.0
        ],
        [
          70.0,
          396.0
        ],
        [
          70.0,
          397.0
        ],
        [
          73.0,
          400.0
        ],
        [
          73.0,
          401.0
        ],
        [
          75.0,
          403.0
        ],
        [
          75.0,
          404.0
        ],
        [
          77.0,
          406.0
        ],
        [
          77.0,
          407.0
        ],
        [
          82.0,
          412.0
        ],
        [
          82.0,
          413.0
        ],
        [
          89.0,
          420.0
        ],
        [
          89.0,
          421.0
        ],
        [
          94.0,
          426.0
        ],
        [
          94.0,
          427.0
        ],
        [
          96.0,
          429.0
        ],
        [
          98.0,
          429.0
        ],
        [
          99.0,
          430.0
        ],
        [
          100.0,
          430.0
        ],
        [
          101.0,
          431.0
        ],
        [
          105.0,
          431.0
        ],
        [
          106.0,
          432.0
        ],
        [
          111.0,
          432.0
        ],
        [
          112.0,
          433.0
        ],
        [
          113.0,
          433.0
        ],
        [
          114.0,
          432.0
        ],
        [
          117.0,
          432.0
        ],
        [
          118.0,
          431.0
        ],
        [
          119.0,
          431.0
        ],
        [
          120.0,
          430.0
        ],
        [
          121.0,
          430.0
        ],
        [
          122.0,
          429.0
        ],
        [
          124.0,
          429.0
        ],
        [
          126.0,
          427.0
        ],
        [
          127.0,
          427.0
        ],
        [
          127.0,
          425.0
        ],
        [
          128.0,
          424.0
        ],
        [
          128.0,
          421.0
        ],
        [
          127.0,
          420.0
        ],
        [
          127.0,
          415.0
        ],
        [
          126.0,
          414.0
        ],
        [
          126.0,
          411.0
        ],
        [
          125.0,
          410.0
        ],
        [
          125.0,
          409.0
        ],
        [
          124.0,
          408.0
        ],
        [
          124.0,
          406.0
        ],
        [
          120.0,
          402.0
        ],
        [
          120.0,
          400.0
        ],
        [
          119.0,
          399.0
        ],
        [
          119.0,
          397.0
        ],
        [
          117.0,
          395.0
        ],
        [
          117.0,
          394.0
        ],
        [
          115.0,
          392.0
        ],
        [
          115.0,
          391.0
        ],
        [
          111.0,
          387.0
        ],
        [
          110.0,
          387.0
        ],
        [
          109.0,
          386.0
        ],
        [
          109.0,
          385.0
        ],
        [
          106.0,
          382.0
        ],
        [
          106.0,
          381.0
        ],
        [
          105.0,
          381.0
        ],
        [
          103.0,
          379.0
        ],
        [
          102.0,
          379.0
        ],
        [
          101.0,
          378.0
        ],
        [
          100.0,
          378.0
        ],
        [
          99.0,
          377.0
        ],
        [
          94.0,
          377.0
        ],
        [
          93.0,
          376.0
        ],
        [
          91.0,
          376.0
        ],
        [
          90.0,
          375.0
        ],
        [
          88.0,
          375.0
        ],
        [
          85.0,
          372.0
        ],
        [
          84.0,
          372.0
        ],
        [
          82.0,
          370.0
        ],
        [
          81.0,
          370.0
        ],
        [
          78.0,
          367.0
        ],
        [
          77.0,
          367.0
        ],
        [
          75.0,
          365.0
        ],
        [
          75.0,
          364.0
        ],
        [
          74.0,
          363.0
        ],
        [
          73.0,
          363.0
        ],
        [
          72.0,
          362.0
        ],
        [
          71.0,
          362.0
        ],
        [
          70.0,
          361.0
        ]
      ],
      "group_id": null,
      "description": null,
      "difficult": false,
      "shape_type": "polygon",
      "flags": {},
      "attributes": {},
      "kie_linking": []
    },
    {
      "label": "Black_Rot",
      "score": null,
      "points": [
        [
          215.0,
          423.0
        ],
        [
          215.0,
          426.0
        ],
        [
          214.0,
          427.0
        ],
        [
          214.0,
          431.0
        ],
        [
          215.0,
          432.0
        ],
        [
          215.0,
          433.0
        ],
        [
          217.0,
          435.0
        ],
        [
          217.0,
          436.0
        ],
        [
          221.0,
          440.0
        ],
        [
          222.0,
          440.0
        ],
        [
          223.0,
          441.0
        ],
        [
          225.0,
          441.0
        ],
        [
          226.0,
          442.0
        ],
        [
          228.0,
          442.0
        ],
        [
          229.0,
          443.0
        ],
        [
          235.0,
          443.0
        ],
        [
          236.0,
          442.0
        ],
        [
          237.0,
          442.0
        ],
        [
          238.0,
          441.0
        ],
        [
          240.0,
          441.0
        ],
        [
          247.0,
          434.0
        ],
        [
          247.0,
          432.0
        ],
        [
          248.0,
          431.0
        ],
        [
          248.0,
          426.0
        ],
        [
          247.0,
          425.0
        ],
        [
          247.0,
          423.0
        ],
        [
          243.0,
          419.0
        ],
        [
          242.0,
          419.0
        ],
        [
          241.0,
          418.0
        ],
        [
          239.0,
          418.0
        ],
        [
          238.0,
          417.0
        ],
        [
          237.0,
          417.0
        ],
        [
          236.0,
          416.0
        ],
        [
          226.0,
          416.0
        ],
        [
          225.0,
          417.0
        ],
        [
          222.0,
          417.0
        ],
        [
          221.0,
          418.0
        ],
        [
          220.0,
          418.0
        ]
      ],
      "group_id": null,
      "description": null,
      "difficult": false,
      "shape_type": "polygon",
      "flags": {},
      "attributes": {},
      "kie_linking": []
    },
    {
      "label": "Black_Rot",
      "score": null,
      "points": [
        [
          192.0,
          461.0
        ],
        [
          192.0,
          467.0
        ],
        [
          195.0,
          470.0
        ],
        [
          196.0,
          470.0
        ],
        [
          197.0,
          471.0
        ],
        [
          198.0,
          471.0
        ],
        [
          199.0,
          472.0
        ],
        [
          200.0,
          472.0
        ],
        [
          201.0,
          473.0
        ],
        [
          202.0,
          473.0
        ],
        [
          203.0,
          474.0
        ],
        [
          205.0,
          474.0
        ],
        [
          206.0,
          475.0
        ],
        [
          208.0,
          475.0
        ],
        [
          209.0,
          476.0
        ],
        [
          217.0,
          476.0
        ],
        [
          218.0,
          475.0
        ],
        [
          219.0,
          475.0
        ],
        [
          220.0,
          474.0
        ],
        [
          221.0,
          474.0
        ],
        [
          223.0,
          472.0
        ],
        [
          223.0,
          466.0
        ],
        [
          219.0,
          462.0
        ],
        [
          218.0,
          462.0
        ],
        [
          215.0,
          459.0
        ],
        [
          208.0,
          459.0
        ],
        [
          207.0,
          458.0
        ],
        [
          206.0,
          459.0
        ],
        [
          195.0,
          459.0
        ],
        [
          195.0,
          460.0
        ],
        [
          194.0,
          461.0
        ]
      ],
      "group_id": null,
      "description": null,
      "difficult": false,
      "shape_type": "polygon",
      "flags": {},
      "attributes": {},
      "kie_linking": []
    },
    {
      "label": "Black_Rot",
      "score": null,
      "points": [
        [
          203.0,
          417.0
        ],
        [
          202.0,
          418.0
        ],
        [
          202.0,
          420.0
        ],
        [
          204.0,
          422.0
        ],
        [
          207.0,
          422.0
        ],
        [
          208.0,
          421.0
        ],
        [
          208.0,
          418.0
        ],
        [
          207.0,
          417.0
        ],
        [
          206.0,
          417.0
        ],
        [
          205.0,
          416.0
        ],
        [
          204.0,
          417.0
        ]
      ],
      "group_id": null,
      "description": null,
      "difficult": false,
      "shape_type": "polygon",
      "flags": {},
      "attributes": {},
      "kie_linking": []
    },
    {
      "label": "Black_Rot",
      "score": null,
      "points": [
        [
          323.0,
          455.0
        ],
        [
          322.0,
          454.0
        ],
        [
          321.0,
          454.0
        ],
        [
          319.0,
          452.0
        ],
        [
          317.0,
          452.0
        ],
        [
          316.0,
          451.0
        ],
        [
          314.0,
          451.0
        ],
        [
          313.0,
          450.0
        ],
        [
          299.0,
          450.0
        ],
        [
          298.0,
          451.0
        ],
        [
          296.0,
          451.0
        ],
        [
          295.0,
          452.0
        ],
        [
          294.0,
          452.0
        ],
        [
          293.0,
          453.0
        ],
        [
          292.0,
          453.0
        ],
        [
          291.0,
          454.0
        ],
        [
          290.0,
          454.0
        ],
        [
          289.0,
          455.0
        ],
        [
          287.0,
          455.0
        ],
        [
          286.0,
          456.0
        ],
        [
          284.0,
          456.0
        ],
        [
          283.0,
          457.0
        ],
        [
          281.0,
          457.0
        ],
        [
          280.0,
          458.0
        ],
        [
          279.0,
          458.0
        ],
        [
          275.0,
          462.0
        ],
        [
          275.0,
          467.0
        ],
        [
          276.0,
          467.0
        ],
        [
          277.0,
          468.0
        ],
        [
          278.0,
          468.0
        ],
        [
          279.0,
          469.0
        ],
        [
          282.0,
          469.0
        ],
        [
          283.0,
          470.0
        ],
        [
          287.0,
          470.0
        ],
        [
          288.0,
          469.0
        ],
        [
          289.0,
          469.0
        ],
        [
          290.0,
          470.0
        ],
        [
          306.0,
          470.0
        ],
        [
          307.0,
          469.0
        ],
        [
          309.0,
          469.0
        ],
        [
          310.0,
          468.0
        ],
        [
          311.0,
          468.0
        ],
        [
          312.0,
          467.0
        ],
        [
          313.0,
          467.0
        ],
        [
          315.0,
          465.0
        ],
        [
          316.0,
          465.0
        ],
        [
          318.0,
          463.0
        ],
        [
          319.0,
          463.0
        ],
        [
          321.0,
          461.0
        ],
        [
          321.0,
          460.0
        ],
        [
          323.0,
          458.0
        ]
      ],
      "group_id": null,
      "description": null,
      "difficult": false,
      "shape_type": "polygon",
      "flags": {},
      "attributes": {},
      "kie_linking": []
    },
    {
      "label": "Black_Rot",
      "score": null,
      "points": [
        [
          375.0,
          354.0
        ],
        [
          374.0,
          354.0
        ],
        [
          373.0,
          353.0
        ],
        [
          371.0,
          353.0
        ],
        [
          370.0,
          352.0
        ],
        [
          368.0,
          352.0
        ],
        [
          367.0,
          353.0
        ],
        [
          364.0,
          353.0
        ],
        [
          362.0,
          355.0
        ],
        [
          361.0,
          355.0
        ],
        [
          356.0,
          360.0
        ],
        [
          356.0,
          362.0
        ],
        [
          355.0,
          363.0
        ],
        [
          355.0,
          367.0
        ],
        [
          356.0,
          368.0
        ],
        [
          356.0,
          369.0
        ],
        [
          357.0,
          370.0
        ],
        [
          358.0,
          370.0
        ],
        [
          359.0,
          371.0
        ],
        [
          366.0,
          371.0
        ],
        [
          368.0,
          369.0
        ],
        [
          369.0,
          369.0
        ],
        [
          372.0,
          366.0
        ],
        [
          372.0,
          365.0
        ],
        [
          375.0,
          362.0
        ],
        [
          375.0,
          361.0
        ],
        [
          376.0,
          360.0
        ],
        [
          376.0,
          356.0
        ],
        [
          375.0,
          355.0
        ]
      ],
      "group_id": null,
      "description": null,
      "difficult": false,
      "shape_type": "polygon",
      "flags": {},
      "attributes": {},
      "kie_linking": []
    },
    {
      "label": "Black_Rot",
      "score": null,
      "points": [
        [
          387.0,
          266.0
        ],
        [
          386.0,
          267.0
        ],
        [
          386.0,
          273.0
        ],
        [
          387.0,
          274.0
        ],
        [
          387.0,
          275.0
        ],
        [
          388.0,
          276.0
        ],
        [
          388.0,
          277.0
        ],
        [
          391.0,
          277.0
        ],
        [
          392.0,
          276.0
        ],
        [
          392.0,
          275.0
        ],
        [
          393.0,
          274.0
        ],
        [
          393.0,
          273.0
        ],
        [
          392.0,
          272.0
        ],
        [
          392.0,
          269.0
        ],
        [
          391.0,
          268.0
        ],
        [
          391.0,
          267.0
        ],
        [
          390.0,
          266.0
        ]
      ],
      "group_id": null,
      "description": null,
      "difficult": false,
      "shape_type": "polygon",
      "flags": {},
      "attributes": {},
      "kie_linking": []
    }
  ],
  "imagePath": "black_rot_0447.jpg",
  "imageData": null,
  "imageHeight": 512,
  "imageWidth": 512
}